puffit/__init__.py
puffit/__main__.py
puffit/generator/__init__.py
puffit/parser/__init__.py
puffit-1.0.5.dist-info/LICENSE
puffit-1.0.5.dist-info/METADATA
puffit-1.0.5.dist-info/WHEEL
puffit-1.0.5.dist-info/entry_points.txt
puffit-1.0.5.dist-info/RECORD
