Metadata-Version: 2.1
Name: puffit
Version: 1.0.5
Summary: puffit generates directory structure from text templates
Author: Bryce Jenkins
Author-email: bryce@durish.xyz
Requires-Python: >=3.9,<=3.12
Classifier: License :: OSI Approved :: MIT License
Classifier: Operating System :: OS Independent
Classifier: Programming Language :: Python :: 3
Classifier: Programming Language :: Python :: 3.9
Classifier: Programming Language :: Python :: 3.10
Classifier: Programming Language :: Python :: 3.11
Classifier: Programming Language :: Python :: 3.12
